{
  "name": "RunCam_ThumbPro_caddx ratel v1_2k_2.7k_16by9_2704x1520-60.00fps",
  "note": "2k",
  "calibrated_by": "Gerald Ong",
  "camera_brand": "RunCam",
  "camera_model": "ThumbPro",
  "lens_model": "caddx ratel v1",
  "camera_setting": "",
  "calib_dimension": {
    "w": 2704,
    "h": 1520
  },
  "orig_dimension": {
    "w": 2704,
    "h": 1520
  },
  "output_dimension": {
    "w": 2704,
    "h": 1520
  },
  "frame_readout_time": null,
  "gyro_lpf": null,
  "input_horizontal_stretch": 1.0,
  "input_vertical_stretch": 1.0,
  "num_images": 15,
  "fps": 60.0,
  "crop": null,
  "official": false,
  "asymmetrical": false,
  "fisheye_params": {
    "RMS_error": 0.5103290797762039,
    "camera_matrix": [
      [
        1216.0859631273595,
        0.0,
        1346.5726131220033
      ],
      [
        0.0,
        1219.3544148860788,
        841.7648832973089
      ],
      [
        0.0,
        0.0,
        1.0
      ]
    ],
    "distortion_coeffs": [
      -0.04029734159195686,
      0.0071964968180885935,
      -0.04008053722461487,
      0.022818727696187625
    ],
    "radial_distortion_limit": null
  },
  "identifier": "",
  "calibrator_version": "1.3.0",
  "date": "2022-11-14",
  "compatible_settings": [],
  "sync_settings": null,
  "distortion_model": null,
  "digital_lens": null,
  "digital_lens_params": null,
  "interpolations": null
}