{
  "name": "Blackmagic_Pocket Cinema Camera 4K_Samyang 12mm T2.2_RAW DCI_C4k_1.90by1_4096x2160-50.00fps",
  "note": "",
  "calibrated_by": "Babang Deshommes",
  "camera_brand": "Blackmagic",
  "camera_model": "Pocket Cinema Camera 4K",
  "lens_model": "Samyang 12mm T2.2",
  "camera_setting": "RAW DCI",
  "calib_dimension": {
    "w": 4096,
    "h": 2160
  },
  "orig_dimension": {
    "w": 4096,
    "h": 2160
  },
  "output_dimension": {
    "w": 4096,
    "h": 2160
  },
  "frame_readout_time": null,
  "gyro_lpf": null,
  "input_horizontal_stretch": 1.0,
  "input_vertical_stretch": 1.0,
  "num_images": 15,
  "fps": 50.0,
  "crop": null,
  "official": false,
  "asymmetrical": false,
  "fisheye_params": {
    "RMS_error": 1.6258540302119893,
    "camera_matrix": [
      [
        2970.864994822542,
        0.0,
        2007.6910891513496
      ],
      [
        0.0,
        2966.213240324684,
        1071.8153840549387
      ],
      [
        0.0,
        0.0,
        1.0
      ]
    ],
    "distortion_coeffs": [
      0.3105410108714532,
      -0.11382213554693582,
      1.0206865262848506,
      -1.3952620282196329
    ],
    "radial_distortion_limit": null
  },
  "identifier": "",
  "calibrator_version": "1.5.0",
  "date": "2023-03-15",
  "compatible_settings": [],
  "sync_settings": null,
  "distortion_model": null,
  "digital_lens": null,
  "digital_lens_params": null,
  "interpolations": null,
  "focal_length": null,
  "crop_factor": null,
  "global_shutter": false
}