{
  "name": "Blackmagic_Pocket Cinema Camera 6k_DZOFILM 35mm T2.1_RAW 12:1_6k_16by9_6144x3456-50.00fps",
  "note": "",
  "calibrated_by": "尚文",
  "camera_brand": "Blackmagic",
  "camera_model": "Pocket Cinema Camera 6k",
  "lens_model": "DZOFILM 35mm T2.1",
  "camera_setting": "RAW 12:1",
  "calib_dimension": {
    "w": 6144,
    "h": 3456
  },
  "orig_dimension": {
    "w": 6144,
    "h": 3456
  },
  "output_dimension": {
    "w": 6144,
    "h": 3456
  },
  "frame_readout_time": null,
  "gyro_lpf": null,
  "input_horizontal_stretch": 1.0,
  "input_vertical_stretch": 1.0,
  "num_images": 15,
  "fps": 50.0,
  "crop": null,
  "official": false,
  "asymmetrical": false,
  "fisheye_params": {
    "RMS_error": 0.7985856435284105,
    "camera_matrix": [
      [
        9067.10075187364,
        0.0,
        3206.474451255647
      ],
      [
        0.0,
        9067.42110037204,
        1844.4091111441492
      ],
      [
        0.0,
        0.0,
        1.0
      ]
    ],
    "distortion_coeffs": [
      0.19864455352150123,
      -0.20948139613874223,
      3.675774663434993,
      -8.644196951522854
    ],
    "radial_distortion_limit": null
  },
  "identifier": "",
  "calibrator_version": "1.3.0",
  "date": "",
  "compatible_settings": [],
  "sync_settings": null,
  "distortion_model": null,
  "digital_lens": null,
  "digital_lens_params": null,
  "interpolations": null
}