{
  "name": "RED_KOMODO_Laowa 9mm_9mm_6k_1.90by1_6144x3240-25.00fps",
  "note": "9mm",
  "calibrated_by": "SELARL Landreat",
  "camera_brand": "RED",
  "camera_model": "KOMODO",
  "lens_model": "Laowa 9mm",
  "camera_setting": "9mm",
  "calib_dimension": {
    "w": 6144,
    "h": 3240
  },
  "orig_dimension": {
    "w": 6144,
    "h": 3240
  },
  "output_dimension": {
    "w": 6144,
    "h": 3240
  },
  "global_shutter": true,
  "gyro_lpf": null,
  "input_horizontal_stretch": 1.0,
  "num_images": 5,
  "fps": 25.0,
  "official": false,
  "use_opencv_fisheye": true,
  "fisheye_params": {
    "RMS_error": 0.45578769974035976,
    "camera_matrix": [
      [
        2103.5124733529333,
        0.0,
        3097.384857938895
      ],
      [
        0.0,
        2104.2263407315113,
        1617.7980688377295
      ],
      [
        0.0,
        0.0,
        1.0
      ]
    ],
    "distortion_coeffs": [
      0.3409642151890979,
      0.13554211673287306,
      -0.04383734814365183,
      0.11906230722581916
    ],
    "radial_distortion_limit": null
  },
  "use_opencv_standard": false,
  "calib_params": {
    "RMS_error": 0.0,
    "camera_matrix": [],
    "distortion_coeffs": [],
    "radial_distortion_limit": null
  },
  "identifier": "",
  "calibrator_version": "1.0.0-rc4",
  "date": "2022-03-21",
  "compatible_settings": [],
  "frame_readout_time": null,
  "focal_length": 9.0,
  "sync_settings": {
    "initial_offset": 0,
    "initial_offset_inv": false,
    "search_size": 0.5,
    "max_sync_points": 3,
    "every_nth_frame": 1,
    "time_per_syncpoint": 0.5,
    "do_autosync": true
  }
}