{
  "name": "RED_KOMODO 6K_Meike 50mm FF Cine, Canon Speedbooster_6K 17:9_6k_1.90by1_6910x3645-25.00fps",
  "note": "",
  "calibrated_by": "Mikołaj Szczepka",
  "camera_brand": "RED",
  "camera_model": "KOMODO 6K",
  "lens_model": "Meike 50mm FF Cine, Canon Speedbooster",
  "camera_setting": "6K 17:9",
  "calib_dimension": {
    "w": 6910,
    "h": 3645
  },
  "orig_dimension": {
    "w": 6910,
    "h": 3645
  },
  "output_dimension": {
    "w": 6144,
    "h": 3240
  },
  "frame_readout_time": null,
  "gyro_lpf": null,
  "input_horizontal_stretch": 1.0,
  "input_vertical_stretch": 1.0,
  "num_images": 15,
  "fps": 25.0,
  "crop": null,
  "official": false,
  "asymmetrical": false,
  "fisheye_params": {
    "RMS_error": 1.255007947424131,
    "camera_matrix": [
      [
        9195.536024912495,
        0.0,
        3452.370273655592
      ],
      [
        0.0,
        9203.771233420472,
        1835.4226754371275
      ],
      [
        0.0,
        0.0,
        1.0
      ]
    ],
    "distortion_coeffs": [
      0.1874990051984505,
      1.1752122382589432,
      -7.953840306599001,
      38.9429081328903
    ],
    "radial_distortion_limit": null
  },
  "identifier": "",
  "calibrator_version": "1.5.0",
  "date": "2023-04-03",
  "compatible_settings": [],
  "sync_settings": null,
  "distortion_model": null,
  "digital_lens": null,
  "digital_lens_params": null,
  "interpolations": null,
  "focal_length": null,
  "crop_factor": null,
  "global_shutter": true
}